cepton_sdk2/__init__.py
cepton_sdk2/c.py
cepton_sdk2/frame.py
cepton_sdk2/sdk.py
cepton_sdk2/sensor.py
cepton_sdk2/soa.py
cepton_sdk2/__pycache__/__init__.cpython-311.pyc
cepton_sdk2/__pycache__/c.cpython-311.pyc
cepton_sdk2/__pycache__/frame.cpython-311.pyc
cepton_sdk2/__pycache__/sdk.cpython-311.pyc
cepton_sdk2/__pycache__/sensor.cpython-311.pyc
cepton_sdk2/__pycache__/soa.cpython-311.pyc
cepton_sdk2/lib/darwin-arm64/libcepton_sdk.dylib
cepton_sdk2/lib/darwin-arm64/libcepton_sdk2.dylib
cepton_sdk2/lib/darwin-x64/libcepton_sdk.dylib
cepton_sdk2/lib/darwin-x64/libcepton_sdk2.dylib
cepton_sdk2/lib/linux-arm64/libcepton_sdk.so
cepton_sdk2/lib/linux-arm64/libcepton_sdk2.so
cepton_sdk2/lib/linux-x64/libcepton_sdk.so
cepton_sdk2/lib/linux-x64/libcepton_sdk2.so
cepton_sdk2/lib/win32-x64/cepton_sdk.dll
cepton_sdk2/lib/win32-x64/cepton_sdk2.dll
cepton_sdk2/lib/win32-x64/cepton_sdk2.imp.lib
cepton_sdk2/utils/__init__.py
cepton_sdk2/utils/io.py
cepton_sdk2/utils/__pycache__/__init__.cpython-311.pyc
cepton_sdk2/utils/__pycache__/io.cpython-311.pyc
cepton_sdk2-2.1.4.dist-info/LICENSE
cepton_sdk2-2.1.4.dist-info/METADATA
cepton_sdk2-2.1.4.dist-info/WHEEL
cepton_sdk2-2.1.4.dist-info/top_level.txt
cepton_sdk2-2.1.4.dist-info/zip-safe
cepton_sdk2-2.1.4.dist-info/RECORD
