Metadata-Version: 2.1
Name: cepton-sdk2
Version: 2.1.4
Summary: Cepton SDK2 Python3 bindings
Home-page: https://www.cepton.com
Author: Cepton Technologies, Inc.
Author-email: dongyi.liao@cepton.com
License: MIT
Classifier: Programming Language :: Python :: 3
Classifier: License :: OSI Approved :: MIT License
Classifier: Operating System :: OS Independent
License-File: LICENSE
Requires-Dist: numpy
